lightworks/__init__.py
lightworks/__settings.py
lightworks/__version.py
lightworks/py.typed
lightworks/emulator/__init__.py
lightworks/emulator/backends/__init__.py
lightworks/emulator/backends/abc_backend.py
lightworks/emulator/backends/backend.py
lightworks/emulator/backends/caching.py
lightworks/emulator/backends/fock_backend.py
lightworks/emulator/backends/permanent.py
lightworks/emulator/backends/slos.py
lightworks/emulator/components/__init__.py
lightworks/emulator/components/detector.py
lightworks/emulator/components/source.py
lightworks/emulator/simulation/__init__.py
lightworks/emulator/simulation/analyzer.py
lightworks/emulator/simulation/probability_distribution.py
lightworks/emulator/simulation/runner.py
lightworks/emulator/simulation/sampler.py
lightworks/emulator/simulation/simulator.py
lightworks/emulator/state/__init__.py
lightworks/emulator/state/annotated_state.py
lightworks/emulator/utils/__init__.py
lightworks/emulator/utils/exceptions.py
lightworks/emulator/utils/sim.py
lightworks/emulator/utils/state.py
lightworks/interferometers/__init__.py
lightworks/interferometers/decomposition.py
lightworks/interferometers/error_model.py
lightworks/interferometers/reck.py
lightworks/interferometers/dists/__init__.py
lightworks/interferometers/dists/constant.py
lightworks/interferometers/dists/distribution.py
lightworks/interferometers/dists/gaussian.py
lightworks/interferometers/dists/top_hat.py
lightworks/interferometers/dists/utils.py
lightworks/qubit/__init__.py
lightworks/qubit/converter/__init__.py
lightworks/qubit/converter/converter.py
lightworks/qubit/converter/qiskit_convert.py
lightworks/qubit/converter/utils.py
lightworks/qubit/gates/__init__.py
lightworks/qubit/gates/single_qubit_gates.py
lightworks/qubit/gates/three_qubit_gates.py
lightworks/qubit/gates/two_qubit_gates.py
lightworks/sdk/__init__.py
lightworks/sdk/circuit/__init__.py
lightworks/sdk/circuit/parameters.py
lightworks/sdk/circuit/photonic_circuit.py
lightworks-2.3.2.dist-info/licenses/LICENSE
lightworks-2.3.2.dist-info/METADATA
lightworks-2.3.2.dist-info/WHEEL
lightworks-2.3.2.dist-info/top_level.txt
lightworks-2.3.2.dist-info/RECORD
