Metadata-Version: 2.4
Name: lightworks
Version: 2.3.2
Summary: Open-source Python SDK for photonic quantum computation.
Home-page: https://github.com/Aegiq/lightworks
Author: Aegiq Ltd.
License: Apache 2.0
Project-URL: Source, https://github.com/Aegiq/lightworks
Project-URL: Documentation, https://aegiq.github.io/lightworks/
Classifier: License :: OSI Approved :: Apache Software License
Classifier: Natural Language :: English
Classifier: Programming Language :: Python
Classifier: Programming Language :: Python :: 3.10
Classifier: Programming Language :: Python :: 3.11
Classifier: Programming Language :: Python :: 3.12
Classifier: Programming Language :: Python :: 3.13
Classifier: Programming Language :: Python :: 3.14
Classifier: Operating System :: OS Independent
Requires-Python: >=3.10
License-File: LICENSE
Requires-Dist: thewalrus==0.20.0
Requires-Dist: matplotlib>=3.7.1
Requires-Dist: pandas>=2.0.1
Requires-Dist: numpy>=1.24.3
Requires-Dist: multimethod>=1.11.2
Requires-Dist: drawsvg>=2.3.0
Requires-Dist: CairoSVG>=2.8.0
Requires-Dist: sympy>=1.12.0
Requires-Dist: pyarrow
Requires-Dist: ipython
Provides-Extra: all
Requires-Dist: lightworks[qiskit,remote]; extra == "all"
Provides-Extra: remote
Requires-Dist: lightworks-remote>=1.2.0; extra == "remote"
Provides-Extra: qiskit
Requires-Dist: qiskit[visualization]>=1.1.0; extra == "qiskit"
Dynamic: author
Dynamic: classifier
Dynamic: description
Dynamic: description-content-type
Dynamic: home-page
Dynamic: license
Dynamic: license-file
Dynamic: project-url
Dynamic: provides-extra
Dynamic: requires-dist
Dynamic: requires-python
Dynamic: summary
